{
  "news_file_ver": true, 
  "news_easy_voice_uri": "k10011100171000.mp3", 
  "title": "北朝鮮　ＩＣＢＭのためにソビエトのエンジンを買った可能性", 
  "news_prearranged_time": "2017-08-16 16:30:00", 
  "news_easy_image_uri": "''", 
  "has_news_easy_image": false, 
  "news_publication_status": true, 
  "outline_with_ruby": "<p><ruby>北朝鮮<rt>きたちょうせん</rt></ruby>は、アメリカまで<ruby>飛<rt>と</rt></ruby>ぶＩＣＢＭという<ruby>新<rt>あたら</rt></ruby>しい<a href='javascript:void(0)' class='dicWin' id='id-0003'>ミサイル</a>を<ruby>作<rt>つく</rt></ruby>っています。", 
  "news_web_movie_uri": "k10011100171_201708151249_201708151252.mp4", 
  "title_with_ruby": "<ruby>北朝鮮<rt>きたちょうせん</rt></ruby>　ＩＣＢＭのためにソビエトのエンジンを<ruby>買<rt>か</rt></ruby>った<ruby>可能性<rt>かのうせい</rt></ruby>", 
  "news_id": "k10011100171000", 
  "has_news_easy_movie": false, 
  "has_news_web_movie": true, 
  "top_display_flag": true, 
  "top_priority_number": "2", 
  "has_news_web_image": true, 
  "has_news_easy_voice": true, 
  "news_web_image_uri": "http://www3.nhk.or.jp/news/html/20170815/../20170815/K10011100171_1708151110_1708151111_01_02.jpg", 
  "news_easy_movie_uri": "''"
}